pydlib/__init__.py
pydlib/dlib.py
pydlib-0.3.2.dist-info/LICENSE
pydlib-0.3.2.dist-info/METADATA
pydlib-0.3.2.dist-info/WHEEL
pydlib-0.3.2.dist-info/top_level.txt
pydlib-0.3.2.dist-info/RECORD
