Metadata-Version: 2.1
Name: pydlib
Version: 0.3.2
Summary: The Dictionary Library.
Home-page: https://github.com/aitechnologies-it/dlib
Author: Luigi Di Sotto, Diego Giorgini
Author-email: l.disotto@gmail.com, diego.giorgini@icloud.com
Project-URL: Bug Tracker, https://github.com/aitechnologies-it/dlib/issues
Classifier: Programming Language :: Python :: 3
Classifier: License :: OSI Approved :: MIT License
Classifier: Operating System :: OS Independent
Requires-Python: >=3.7
License-File: LICENSE
Requires-Dist: flatten-dict
